agent_test/__init__.py
agent_test/cli.py
agent_test/core/__init__.py
agent_test/core/config.py
agent_test/core/decorators.py
agent_test/core/git_logger.py
agent_test/core/init.py
agent_test/core/logging.py
agent_test/core/runner.py
agent_test/evaluators/__init__.py
agent_test/evaluators/base.py
agent_test/evaluators/llm_judge.py
agent_test/evaluators/metrics.py
agent_test/evaluators/registry.py
agent_test/generators/__init__.py
agent_test/generators/test_generator.py
agent_test/utils/__init__.py
agent_test/utils/exceptions.py
agenttest-0.1.0.dist-info/METADATA
agenttest-0.1.0.dist-info/WHEEL
agenttest-0.1.0.dist-info/entry_points.txt
agenttest-0.1.0.dist-info/licenses/LICENSE
agenttest-0.1.0.dist-info/RECORD
