Metadata-Version: 2.4
Name: agenttest
Version: 0.1.0
Summary: A pytest-like testing framework for AI agents and prompts
Project-URL: Homepage, https://github.com/Nihal-Srivastava05/agent-test
Project-URL: Documentation, https://nihal-srivastava05.github.io/agent-test/
Project-URL: Repository, https://github.com/Nihal-Srivastava05/agent-test
Project-URL: Issues, https://github.com/Nihal-Srivastava05/agent-test/issues
Author: AgentTest Contributors
License: MIT
License-File: LICENSE
Keywords: agents,ai,evaluation,llm,pytest,testing
Classifier: Development Status :: 3 - Alpha
Classifier: Environment :: Console
Classifier: Intended Audience :: Developers
Classifier: License :: OSI Approved :: MIT License
Classifier: Operating System :: OS Independent
Classifier: Programming Language :: Python :: 3
Classifier: Programming Language :: Python :: 3.8
Classifier: Programming Language :: Python :: 3.9
Classifier: Programming Language :: Python :: 3.10
Classifier: Programming Language :: Python :: 3.11
Classifier: Programming Language :: Python :: 3.12
Classifier: Topic :: Scientific/Engineering :: Artificial Intelligence
Classifier: Topic :: Software Development :: Testing
Requires-Python: >=3.8
Requires-Dist: aiohttp>=3.8.0
Requires-Dist: anthropic>=0.7.0
Requires-Dist: gitpython>=3.1.0
Requires-Dist: jinja2>=3.1.0
Requires-Dist: nltk>=3.8
Requires-Dist: numpy>=1.21.0
Requires-Dist: openai>=1.0.0
Requires-Dist: pydantic>=2.0.0
Requires-Dist: python-dotenv>=1.0.0
Requires-Dist: pyyaml>=6.0
Requires-Dist: requests>=2.28.0
Requires-Dist: rich>=13.0.0
Requires-Dist: rouge-score>=0.1.2
Requires-Dist: scikit-learn>=1.0.0
Requires-Dist: typer[all]>=0.9.0
Provides-Extra: all
Requires-Dist: black>=22.0.0; extra == 'all'
Requires-Dist: flake8>=5.0.0; extra == 'all'
Requires-Dist: google-cloud-aiplatform>=1.0.0; (python_version >= '3.9') and extra == 'all'
Requires-Dist: google-generativeai>=0.3.0; (python_version >= '3.9') and extra == 'all'
Requires-Dist: isort>=5.10.0; extra == 'all'
Requires-Dist: langchain-anthropic>=0.1.0; extra == 'all'
Requires-Dist: langchain-google-genai>=1.0.0; extra == 'all'
Requires-Dist: langchain-openai>=0.1.0; extra == 'all'
Requires-Dist: langchain>=0.1.0; extra == 'all'
Requires-Dist: llama-index>=0.9.0; extra == 'all'
Requires-Dist: mkdocs-git-committers-plugin-2>=1.2.0; extra == 'all'
Requires-Dist: mkdocs-git-revision-date-localized-plugin>=1.2.0; extra == 'all'
Requires-Dist: mkdocs-material>=9.0.0; extra == 'all'
Requires-Dist: mkdocs-minify-plugin>=0.7.0; extra == 'all'
Requires-Dist: mkdocs-redirects>=1.2.0; extra == 'all'
Requires-Dist: mkdocs>=1.5.0; extra == 'all'
Requires-Dist: mypy>=1.0.0; extra == 'all'
Requires-Dist: pre-commit>=2.15.0; extra == 'all'
Requires-Dist: pymdown-extensions>=10.0.0; extra == 'all'
Requires-Dist: pytest-cov>=4.0.0; extra == 'all'
Requires-Dist: pytest>=7.0.0; extra == 'all'
Provides-Extra: dev
Requires-Dist: black>=22.0.0; extra == 'dev'
Requires-Dist: flake8>=5.0.0; extra == 'dev'
Requires-Dist: isort>=5.10.0; extra == 'dev'
Requires-Dist: mypy>=1.0.0; extra == 'dev'
Requires-Dist: pre-commit>=2.15.0; extra == 'dev'
Requires-Dist: pytest-cov>=4.0.0; extra == 'dev'
Requires-Dist: pytest>=7.0.0; extra == 'dev'
Provides-Extra: docs
Requires-Dist: mkdocs-git-committers-plugin-2>=1.2.0; extra == 'docs'
Requires-Dist: mkdocs-git-revision-date-localized-plugin>=1.2.0; extra == 'docs'
Requires-Dist: mkdocs-material>=9.0.0; extra == 'docs'
Requires-Dist: mkdocs-minify-plugin>=0.7.0; extra == 'docs'
Requires-Dist: mkdocs-redirects>=1.2.0; extra == 'docs'
Requires-Dist: mkdocs>=1.5.0; extra == 'docs'
Requires-Dist: pymdown-extensions>=10.0.0; extra == 'docs'
Provides-Extra: google
Requires-Dist: google-cloud-aiplatform>=1.0.0; (python_version >= '3.9') and extra == 'google'
Requires-Dist: google-generativeai>=0.3.0; (python_version >= '3.9') and extra == 'google'
Provides-Extra: langchain
Requires-Dist: langchain-anthropic>=0.1.0; extra == 'langchain'
Requires-Dist: langchain-google-genai>=1.0.0; extra == 'langchain'
Requires-Dist: langchain-openai>=0.1.0; extra == 'langchain'
Requires-Dist: langchain>=0.1.0; extra == 'langchain'
Provides-Extra: llamaindex
Requires-Dist: llama-index>=0.9.0; extra == 'llamaindex'
